pyrtklib/__init__.py
pyrtklib/pyrtklib.pyi
pyrtklib/pyrtklib.so
pyrtklib-0.2.7.dist-info/METADATA
pyrtklib-0.2.7.dist-info/WHEEL
pyrtklib-0.2.7.dist-info/top_level.txt
pyrtklib-0.2.7.dist-info/RECORD
pyrtklib-0.2.7.dist-info/licenses/LICENSE
