Metadata-Version: 2.4
Name: pyrtklib
Version: 0.2.7
Summary: This is a python binding for rtklib
Home-page: https://github.com/IPNL-POLYU/pyrtklib
Author: Runzhi Hu
Author-email: run-zhi.hu@connect.polyu.hk
License-File: LICENSE
Dynamic: author
Dynamic: author-email
Dynamic: description
Dynamic: description-content-type
Dynamic: home-page
Dynamic: license-file
Dynamic: summary
